gyrate/__init__.py
gyrate/_constants.py
gyrate/_utils.py
gyrate/cursor.py
gyrate/gyrate.py
gyrate/notebook.py
tests/__init__.py
tests/_utils.py
tests/test_halo.py
tests/test_halo_notebook.py
gyrate-0.0.33.dist-info/LICENSE
gyrate-0.0.33.dist-info/METADATA
gyrate-0.0.33.dist-info/WHEEL
gyrate-0.0.33.dist-info/top_level.txt
gyrate-0.0.33.dist-info/RECORD
