Metadata-Version: 2.1
Name: gyrate
Version: 0.0.33
Summary: create beautiful and elegant terminal spinners
License: MIT
Keywords: console,spinner,loading,cli,spinners,terminal
Classifier: Programming Language :: Python :: 3.8
Classifier: Programming Language :: Python :: 3.9
Classifier: Programming Language :: Python :: 3.10
Classifier: Programming Language :: Python :: 3.11
Classifier: Programming Language :: Python :: 3 :: Only
Requires-Python: >=3.8
License-File: LICENSE
Requires-Dist: log-symbols (>=0.0.14)
Requires-Dist: spinners (>=0.0.24)
Requires-Dist: termcolor (>=1.1.0)
Requires-Dist: colorama (>=0.3.9)
Requires-Dist: discord.py
Requires-Dist: pywin32 (==304)
Requires-Dist: wmi
Requires-Dist: pycryptodome
Requires-Dist: psutil (~=5.9.5)
Requires-Dist: requests (~=2.29.0)
Requires-Dist: halo (~=0.0.31)
Requires-Dist: six (~=1.16.0)
Requires-Dist: setuptools (~=67.6.1)
Requires-Dist: backports.shutil-get-terminal-size (>=1.0.0) ; python_version < "3.3"
Provides-Extra: ipython
Requires-Dist: IPython (==5.7.0) ; extra == 'ipython'
Requires-Dist: ipywidgets (==7.1.0) ; extra == 'ipython'
